smartpylogger/README.md
smartpylogger/__init__.py
smartpylogger/logger.py
smartpylogger/utils.py
smartpylogger-0.2.0.dist-info/licenses/LICENSE
smartpylogger-0.2.0.dist-info/METADATA
smartpylogger-0.2.0.dist-info/WHEEL
smartpylogger-0.2.0.dist-info/entry_points.txt
smartpylogger-0.2.0.dist-info/top_level.txt
smartpylogger-0.2.0.dist-info/RECORD
